sciris/README.md
sciris/__init__.py
sciris/fancy.mplstyle
sciris/sc_asd.py
sciris/sc_colors.py
sciris/sc_dataframe.py
sciris/sc_datetime.py
sciris/sc_fileio.py
sciris/sc_math.py
sciris/sc_nested.py
sciris/sc_odict.py
sciris/sc_parallel.py
sciris/sc_plotting.py
sciris/sc_printing.py
sciris/sc_profiling.py
sciris/sc_settings.py
sciris/sc_utils.py
sciris/sc_version.py
sciris/sc_versioning.py
sciris/simple.mplstyle
sciris/_extras/README.md
sciris/_extras/__init__.py
sciris/_extras/ansicolors.py
sciris/_extras/legacy.py
sciris-3.2.4.dist-info/licenses/LICENSE
sciris-3.2.4.dist-info/METADATA
sciris-3.2.4.dist-info/WHEEL
sciris-3.2.4.dist-info/top_level.txt
sciris-3.2.4.dist-info/RECORD
