Metadata-Version: 2.4
Name: sciris
Version: 3.2.4
Summary: Fast, flexible tools to simplify scientific Python
Author-email: Sciris Development Team <info@sciris.org>
License-Expression: MIT
Project-URL: Website, https://sciris.org
Project-URL: Source, https://github.com/sciris/sciris/
Keywords: scientific Python,utilities,dates,file I/O,data structures,dataframes,plotting,colormaps,parallelization,math,optimization,versioning
Classifier: Development Status :: 5 - Production/Stable
Classifier: Intended Audience :: Science/Research
Classifier: Operating System :: OS Independent
Classifier: Programming Language :: Python
Classifier: Programming Language :: Python :: 3
Classifier: Programming Language :: Python :: 3.9
Classifier: Programming Language :: Python :: 3.10
Classifier: Programming Language :: Python :: 3.11
Classifier: Programming Language :: Python :: 3.12
Classifier: Programming Language :: Python :: 3.13
Classifier: Topic :: Software Development
Classifier: Topic :: Scientific/Engineering
Requires-Python: >=3.9
License-File: LICENSE
Requires-Dist: numpy
Requires-Dist: pandas
Requires-Dist: matplotlib
Requires-Dist: openpyxl
Requires-Dist: xlsxwriter
Requires-Dist: psutil
Requires-Dist: dill
Requires-Dist: zstandard
Requires-Dist: multiprocess
Requires-Dist: jsonpickle
Requires-Dist: pyyaml
Requires-Dist: packaging
Requires-Dist: setuptools
Requires-Dist: gitpython
Requires-Dist: jellyfish
Requires-Dist: tqdm
Requires-Dist: python-dateutil
Requires-Dist: memory_profiler
Requires-Dist: line_profiler
Requires-Dist: colorama; platform_system == "Windows"
Dynamic: license-file
